opentool/__init__.py
opentool/base.py
opentool/function/__init__.py
opentool/function/exceptions.py
opentool/function/func.py
opentool/function/json_type.py
opentool/function/parsers/__init__.py
opentool/function/parsers/abc.py
opentool/function/parsers/atomic_type_parser.py
opentool/function/parsers/bool_parser.py
opentool/function/parsers/dataclass_parser.py
opentool/function/parsers/default.py
opentool/function/parsers/dict_parser.py
opentool/function/parsers/enum_parser.py
opentool/function/parsers/float_parser.py
opentool/function/parsers/int_parser.py
opentool/function/parsers/list_parser.py
opentool/function/parsers/none_parser.py
opentool/function/parsers/str_parser.py
opentool/function/parsers/union_parser.py
opentool_ai-0.1.10.dist-info/LICENSE
opentool_ai-0.1.10.dist-info/METADATA
opentool_ai-0.1.10.dist-info/WHEEL
opentool_ai-0.1.10.dist-info/entry_points.txt
opentool_ai-0.1.10.dist-info/RECORD
