Metadata-Version: 2.1
Name: opentool-ai
Version: 0.1.10
Summary: A protocol for AI agent tools
License: Apache 2.0
Author: Patrick Barker
Author-email: patrickbarkerco@gmail.com
Requires-Python: >=3.10,<4.0
Classifier: License :: Other/Proprietary License
Classifier: Programming Language :: Python :: 3
Classifier: Programming Language :: Python :: 3.10
Classifier: Programming Language :: Python :: 3.11
Requires-Dist: docstring-parser (>=0.15,<0.16)
Requires-Dist: urllib3 (>=1.26.0,<2.0.0)
